xprpy/__init__.py
xprpy/_version.py
xprpy/exc.py
xprpy/net.py
xprpy/transaction.py
xprpy/types/__init__.py
xprpy/types/base.py
xprpy/types/compostes.py
xprpy/types/primitives.py
xprpy/utils.py
xprpy-1.0.1.dist-info/LICENSE
xprpy-1.0.1.dist-info/METADATA
xprpy-1.0.1.dist-info/WHEEL
xprpy-1.0.1.dist-info/RECORD
