Metadata-Version: 2.1
Name: xprpy
Version: 1.0.1
Summary: Interact with XPR Network blockchain
Home-page: https://github.com/paulgnz/xprpy
Author: Team
Author-email: consoritum@xprnetwork.org
Requires-Python: >=3.8,<4.0
Classifier: Programming Language :: Python :: 3
Classifier: Programming Language :: Python :: 3.8
Classifier: Programming Language :: Python :: 3.9
Classifier: Programming Language :: Python :: 3.10
Classifier: Programming Language :: Python :: 3.11
Classifier: Programming Language :: Python :: 3.12
Classifier: Programming Language :: Python :: 3.13
Requires-Dist: base58 (>=2.1.1,<3.0.0)
Requires-Dist: httpx (>=0.22)
Requires-Dist: pycryptodome (>=3.15.0,<4.0.0)
Requires-Dist: pydantic (>=2.9.0,<3.0.0)
